atakama/__init__.py
atakama/packager.py
atakama/plugin_base.py
atakama/rule_engine.py
atakama-1.9.3.dist-info/LICENSE
atakama-1.9.3.dist-info/METADATA
atakama-1.9.3.dist-info/WHEEL
atakama-1.9.3.dist-info/entry_points.txt
atakama-1.9.3.dist-info/license_header.txt
atakama-1.9.3.dist-info/top_level.txt
atakama-1.9.3.dist-info/RECORD
