Metadata-Version: 2.1
Name: atakama
Version: 1.9.3
Summary: Atakama sdk
Home-page: UNKNOWN
License: UNKNOWN
Platform: UNKNOWN
Requires-Dist: oscrypto
Requires-Dist: certvalidator
